prgen/__init__.py
prgen/main.py
prgen-0.0.3.dist-info/licenses/LICENSE
prgen-0.0.3.dist-info/METADATA
prgen-0.0.3.dist-info/WHEEL
prgen-0.0.3.dist-info/entry_points.txt
prgen-0.0.3.dist-info/top_level.txt
prgen-0.0.3.dist-info/RECORD
