Metadata-Version: 2.4
Name: prgen
Version: 0.0.3
Summary: CLI tool to autogenerate GitHub PRs
Author-email: lugen4ro <lugen4ro@gmail.com>
License-Expression: MIT
Project-URL: source, https://github.com/lugen4ro/prgen
Project-URL: issues, https://github.com/lugen4ro/prgen/issues
Classifier: Programming Language :: Python :: 3
Classifier: Operating System :: OS Independent
Requires-Python: >=3.9
License-File: LICENSE
Dynamic: license-file
